gbmessserver12345/__init__.py
gbmessserver12345/server.py
gbmessserver12345/common/__init__.py
gbmessserver12345/common/transport/__init__.py
gbmessserver12345/common/transport/descriptors.py
gbmessserver12345/common/transport/endpoints.py
gbmessserver12345/common/transport/errors.py
gbmessserver12345/common/transport/metaclasses.py
gbmessserver12345/common/transport/protocol.py
gbmessserver12345/common/transport/security.py
gbmessserver12345/common/transport/model/__init__.py
gbmessserver12345/common/transport/model/message.py
gbmessserver12345/common/transport/model/user.py
gbmessserver12345/common/transport/serializers/__init__.py
gbmessserver12345/common/transport/serializers/message.py
gbmessserver12345/common/transport/serializers/user.py
gbmessserver12345/common/utils/__init__.py
gbmessserver12345/common/utils/debug_decorators.py
gbmessserver12345/common/utils/observer.py
gbmessserver12345/common/utils/security.py
gbmessserver12345/server/__init__.py
gbmessserver12345/server/app.py
gbmessserver12345/server/cli.py
gbmessserver12345/server/config.py
gbmessserver12345/server/errors.py
gbmessserver12345/server/logger.py
gbmessserver12345/server/core/__init__.py
gbmessserver12345/server/core/app.py
gbmessserver12345/server/core/auth.py
gbmessserver12345/server/core/client_session.py
gbmessserver12345/server/core/errors.py
gbmessserver12345/server/core/model.py
gbmessserver12345/server/core/serializers.py
gbmessserver12345/server/core/session_manager.py
gbmessserver12345/server/db/__init__.py
gbmessserver12345/server/db/config.py
gbmessserver12345/server/db/errors.py
gbmessserver12345/server/db/model.py
gbmessserver12345/server/db/view.py
gbmessserver12345/server/gui/__init__.py
gbmessserver12345/server/gui/app.py
gbmessserver12345/server/gui/controller.py
gbmessserver12345/server/gui/model.py
gbmessserver12345/server/gui/view.py
gbmessserver12345-0.1.2.dist-info/METADATA
gbmessserver12345-0.1.2.dist-info/WHEEL
gbmessserver12345-0.1.2.dist-info/top_level.txt
gbmessserver12345-0.1.2.dist-info/RECORD
