Metadata-Version: 2.1
Name: gbmessserver12345
Version: 0.1.2
Summary: Study project: Async messenger, server part
Author-email: gb/Ivan St <empty@mail.com>
License: MIT License
Classifier: Programming Language :: Python :: 3
Requires-Python: >=3.9.11
Requires-Dist: sqlalchemy (==2.0.17)
Requires-Dist: pyqt5 (==5.15.9)
Requires-Dist: pycryptodomex (==3.18.0)
